{"version":"1.2","metadata":{"language":{"name":"ruby","engine":"ruby","version":"2.6.2"},"client":{"name":"appmap","url":"https://github.com/applandinc/appmap-ruby","version":"0.26.1"},"frameworks":[{"name":"rails","version":"6.0.3.1"},{"name":"rspec","version":"3.9.2"}],"git":{"repository":"git@github.com:applandinc/discourse.git","branch":"master","commit":"32fd4b3aab495794a8b45d85fb5cca2201161e3c","status":["M Gemfile.lock","M config/initializers/150-appmap.rb","D spec/requests/posts_controller_spec.rb","M spec/requests/user_actions_controller_spec.rb","M spec/requests/users_controller_spec.rb"],"git_last_annotated_tag":"v2.5.0.beta5","git_last_tag":"v2.5.0.beta5","git_commits_since_last_annotated_tag":0,"git_commits_since_last_tag":0},"name":"UsersController #destroy_user_image raises an error when not logged in","app":"Discourse","feature":"UsersController #destroy_user_image","feature_group":"Users","recorder":{"name":"rspec"}},"classMap":[{"name":"app/models","type":"package","children":[{"name":"LocaleSiteSetting","type":"class","children":[{"name":"fallback_locale","type":"function","location":"app/models/locale_site_setting.rb:62","static":true}]},{"name":"GlobalSetting","type":"class","children":[{"name":"skip_db?","type":"function","location":"app/models/global_setting.rb:84","static":true}]},{"name":"ApplicationRequest(id: integer, date: date, req_type: integer, count: integer)","type":"class","children":[{"name":"increment!","type":"function","location":"app/models/application_request.rb:26","static":true}]}]},{"name":"app/controllers","type":"package","children":[{"name":"ApplicationController","type":"class","children":[{"name":"handle_theme","type":"function","location":"app/controllers/application_controller.rb:388","static":false},{"name":"resolve_safe_mode","type":"function","location":"app/controllers/application_controller.rb:377","static":false},{"name":"guardian","type":"function","location":"app/controllers/application_controller.rb:423","static":false},{"name":"set_current_user_for_logs","type":"function","location":"app/controllers/application_controller.rb:294","static":false},{"name":"clear_notifications","type":"function","location":"app/controllers/application_controller.rb:302","static":false},{"name":"set_locale","type":"function","location":"app/controllers/application_controller.rb:328","static":false},{"name":"set_mobile_view","type":"function","location":"app/controllers/application_controller.rb:368","static":false},{"name":"requires_login_arg","type":"function","location":"app/controllers/application_controller.rb:669","static":true},{"name":"rescue_discourse_actions","type":"function","location":"app/controllers/application_controller.rb:229","static":false}]}]},{"name":"lib/auth","type":"package","children":[{"name":"Auth","type":"class","children":[{"name":"DefaultCurrentUserProvider","type":"class","children":[{"name":"current_user","type":"function","location":"lib/auth/default_current_user_provider.rb:61","static":false},{"name":"is_api?","type":"function","location":"lib/auth/default_current_user_provider.rb:271","static":false},{"name":"has_auth_cookie?","type":"function","location":"lib/auth/default_current_user_provider.rb:281","static":false}]}]}]},{"name":"lib/guardian","type":"package","children":[{"name":"Guardian","type":"class","children":[{"name":"can_enable_safe_mode?","type":"function","location":"lib/guardian.rb:149","static":false},{"name":"allow_themes?","type":"function","location":"lib/guardian.rb:474","static":false}]}]}],"events":[{"id":812291,"event":"call","defined_class":"LocaleSiteSetting","method_id":"fallback_locale","path":"app/models/locale_site_setting.rb","lineno":62,"static":true,"thread_id":70097708498960,"parameters":[{"name":"locale","class":"Symbol","object_id":70097724306540,"value":"en_US","kind":"req"}],"receiver":{"class":"Class","object_id":70097569845280,"value":"LocaleSiteSetting"}},{"id":812292,"event":"return","defined_class":"LocaleSiteSetting","method_id":"fallback_locale","path":"app/models/locale_site_setting.rb","lineno":62,"static":true,"thread_id":70097708498960,"parent_id":812291,"elapsed":6.0e-06,"return_value":{"class":"Symbol","value":"en","object_id":3894428}},{"id":812293,"event":"call","defined_class":"LocaleSiteSetting","method_id":"fallback_locale","path":"app/models/locale_site_setting.rb","lineno":62,"static":true,"thread_id":70097708498960,"parameters":[{"name":"locale","class":"Symbol","object_id":3894428,"value":"en","kind":"req"}],"receiver":{"class":"Class","object_id":70097569845280,"value":"LocaleSiteSetting"}},{"id":812294,"event":"return","defined_class":"LocaleSiteSetting","method_id":"fallback_locale","path":"app/models/locale_site_setting.rb","lineno":62,"static":true,"thread_id":70097708498960,"parent_id":812293,"elapsed":1.1e-05},{"id":812295,"event":"call","defined_class":"AppMap::Rails::ActionHandler::HTTPServerRequest","method_id":"call","path":"/Users/kgilpin/source/appland/appmap-ruby/lib/appmap/rails/action_handler.rb","lineno":50,"static":false,"thread_id":70097708498960,"http_server_request":{"request_method":"DELETE","path_info":"/u/asdf/preferences/user_image.json"},"message":[{"name":"type","class":"String","value":"profile_background","object_id":70097732532040},{"name":"controller","class":"String","value":"users","object_id":70097800810280},{"name":"action","class":"String","value":"destroy_user_image","object_id":70097800810260},{"name":"username","class":"String","value":"asdf","object_id":70097732516540},{"name":"format","class":"String","value":"json","object_id":70097732516520}]},{"id":812296,"event":"call","defined_class":"ApplicationController","method_id":"handle_theme","path":"app/controllers/application_controller.rb","lineno":388,"static":false,"thread_id":70097708498960,"parameters":[],"receiver":{"class":"UsersController","object_id":70097732515280,"value":"#<UsersController:0x00007f81cce46ba0>"}},{"id":812297,"event":"call","defined_class":"ApplicationController","method_id":"resolve_safe_mode","path":"app/controllers/application_controller.rb","lineno":377,"static":false,"thread_id":70097708498960,"parameters":[],"receiver":{"class":"UsersController","object_id":70097732515280,"value":"#<UsersController:0x00007f81cce46ba0>"}},{"id":812298,"event":"call","defined_class":"ApplicationController","method_id":"guardian","path":"app/controllers/application_controller.rb","lineno":423,"static":false,"thread_id":70097708498960,"parameters":[],"receiver":{"class":"UsersController","object_id":70097732515280,"value":"#<UsersController:0x00007f81cce46ba0>"}},{"id":812299,"event":"call","defined_class":"Auth::DefaultCurrentUserProvider","method_id":"current_user","path":"lib/auth/default_current_user_provider.rb","lineno":61,"static":false,"thread_id":70097708498960,"parameters":[],"receiver":{"class":"TestCurrentUserProvider","object_id":70097732732120,"value":"#<TestCurrentUserProvider:0x00007f81cceb09b0>"}},{"id":812300,"event":"return","defined_class":"Auth::DefaultCurrentUserProvider","method_id":"current_user","path":"lib/auth/default_current_user_provider.rb","lineno":61,"static":false,"thread_id":70097708498960,"parent_id":812299,"elapsed":2.6e-05},{"id":812301,"event":"return","defined_class":"ApplicationController","method_id":"guardian","path":"app/controllers/application_controller.rb","lineno":423,"static":false,"thread_id":70097708498960,"parent_id":812298,"elapsed":0.000143,"return_value":{"class":"Guardian","value":"#<Guardian:0x00007f81cceba4d8>","object_id":70097732751980}},{"id":812302,"event":"call","defined_class":"Guardian","method_id":"can_enable_safe_mode?","path":"lib/guardian.rb","lineno":149,"static":false,"thread_id":70097708498960,"parameters":[],"receiver":{"class":"Guardian","object_id":70097732751980,"value":"#<Guardian:0x00007f81cceba4d8>"}},{"id":812303,"event":"return","defined_class":"Guardian","method_id":"can_enable_safe_mode?","path":"lib/guardian.rb","lineno":149,"static":false,"thread_id":70097708498960,"parent_id":812302,"elapsed":9.0e-06,"return_value":{"class":"TrueClass","value":"true","object_id":20}},{"id":812304,"event":"return","defined_class":"ApplicationController","method_id":"resolve_safe_mode","path":"app/controllers/application_controller.rb","lineno":377,"static":false,"thread_id":70097708498960,"parent_id":812297,"elapsed":0.000373},{"id":812305,"event":"call","defined_class":"Auth::DefaultCurrentUserProvider","method_id":"current_user","path":"lib/auth/default_current_user_provider.rb","lineno":61,"static":false,"thread_id":70097708498960,"parameters":[],"receiver":{"class":"TestCurrentUserProvider","object_id":70097732732120,"value":"#<TestCurrentUserProvider:0x00007f81cceb09b0>"}},{"id":812306,"event":"return","defined_class":"Auth::DefaultCurrentUserProvider","method_id":"current_user","path":"lib/auth/default_current_user_provider.rb","lineno":61,"static":false,"thread_id":70097708498960,"parent_id":812305,"elapsed":3.0e-06},{"id":812307,"event":"call","defined_class":"ApplicationController","method_id":"guardian","path":"app/controllers/application_controller.rb","lineno":423,"static":false,"thread_id":70097708498960,"parameters":[],"receiver":{"class":"UsersController","object_id":70097732515280,"value":"#<UsersController:0x00007f81cce46ba0>"}},{"id":812308,"event":"return","defined_class":"ApplicationController","method_id":"guardian","path":"app/controllers/application_controller.rb","lineno":423,"static":false,"thread_id":70097708498960,"parent_id":812307,"elapsed":3.0e-06,"return_value":{"class":"Guardian","value":"#<Guardian:0x00007f81cceba4d8>","object_id":70097732751980}},{"id":812309,"event":"call","defined_class":"Guardian","method_id":"allow_themes?","path":"lib/guardian.rb","lineno":474,"static":false,"thread_id":70097708498960,"parameters":[{"name":"theme_ids","class":"Array","object_id":70097732767100,"value":"[]","kind":"req"},{"name":"include_preview","class":"NilClass","object_id":8,"value":null,"kind":"key"}],"receiver":{"class":"Guardian","object_id":70097732751980,"value":"#<Guardian:0x00007f81cceba4d8>"}},{"id":812310,"event":"return","defined_class":"Guardian","method_id":"allow_themes?","path":"lib/guardian.rb","lineno":474,"static":false,"thread_id":70097708498960,"parent_id":812309,"elapsed":3.0e-06,"return_value":{"class":"TrueClass","value":"true","object_id":20}},{"id":812311,"event":"return","defined_class":"ApplicationController","method_id":"handle_theme","path":"app/controllers/application_controller.rb","lineno":388,"static":false,"thread_id":70097708498960,"parent_id":812296,"elapsed":0.000814,"return_value":{"class":"Array","value":"[2]","object_id":70097732767100}},{"id":812312,"event":"call","defined_class":"ApplicationController","method_id":"set_current_user_for_logs","path":"app/controllers/application_controller.rb","lineno":294,"static":false,"thread_id":70097708498960,"parameters":[],"receiver":{"class":"UsersController","object_id":70097732515280,"value":"#<UsersController:0x00007f81cce46ba0>"}},{"id":812313,"event":"call","defined_class":"Auth::DefaultCurrentUserProvider","method_id":"current_user","path":"lib/auth/default_current_user_provider.rb","lineno":61,"static":false,"thread_id":70097708498960,"parameters":[],"receiver":{"class":"TestCurrentUserProvider","object_id":70097732732120,"value":"#<TestCurrentUserProvider:0x00007f81cceb09b0>"}},{"id":812314,"event":"return","defined_class":"Auth::DefaultCurrentUserProvider","method_id":"current_user","path":"lib/auth/default_current_user_provider.rb","lineno":61,"static":false,"thread_id":70097708498960,"parent_id":812313,"elapsed":3.0e-06},{"id":812315,"event":"return","defined_class":"ApplicationController","method_id":"set_current_user_for_logs","path":"app/controllers/application_controller.rb","lineno":294,"static":false,"thread_id":70097708498960,"parent_id":812312,"elapsed":0.000112,"return_value":{"class":"String","value":"users/destroy_user_image","object_id":70097732801720}},{"id":812316,"event":"call","defined_class":"ApplicationController","method_id":"clear_notifications","path":"app/controllers/application_controller.rb","lineno":302,"static":false,"thread_id":70097708498960,"parameters":[],"receiver":{"class":"UsersController","object_id":70097732515280,"value":"#<UsersController:0x00007f81cce46ba0>"}},{"id":812317,"event":"call","defined_class":"Auth::DefaultCurrentUserProvider","method_id":"current_user","path":"lib/auth/default_current_user_provider.rb","lineno":61,"static":false,"thread_id":70097708498960,"parameters":[],"receiver":{"class":"TestCurrentUserProvider","object_id":70097732732120,"value":"#<TestCurrentUserProvider:0x00007f81cceb09b0>"}},{"id":812318,"event":"return","defined_class":"Auth::DefaultCurrentUserProvider","method_id":"current_user","path":"lib/auth/default_current_user_provider.rb","lineno":61,"static":false,"thread_id":70097708498960,"parent_id":812317,"elapsed":3.0e-06},{"id":812319,"event":"return","defined_class":"ApplicationController","method_id":"clear_notifications","path":"app/controllers/application_controller.rb","lineno":302,"static":false,"thread_id":70097708498960,"parent_id":812316,"elapsed":9.2e-05},{"id":812320,"event":"call","defined_class":"ApplicationController","method_id":"set_locale","path":"app/controllers/application_controller.rb","lineno":328,"static":false,"thread_id":70097708498960,"parameters":[],"receiver":{"class":"UsersController","object_id":70097732515280,"value":"#<UsersController:0x00007f81cce46ba0>"}},{"id":812321,"event":"call","defined_class":"Auth::DefaultCurrentUserProvider","method_id":"current_user","path":"lib/auth/default_current_user_provider.rb","lineno":61,"static":false,"thread_id":70097708498960,"parameters":[],"receiver":{"class":"TestCurrentUserProvider","object_id":70097732732120,"value":"#<TestCurrentUserProvider:0x00007f81cceb09b0>"}},{"id":812322,"event":"return","defined_class":"Auth::DefaultCurrentUserProvider","method_id":"current_user","path":"lib/auth/default_current_user_provider.rb","lineno":61,"static":false,"thread_id":70097708498960,"parent_id":812321,"elapsed":3.0e-06},{"id":812323,"event":"call","defined_class":"LocaleSiteSetting","method_id":"fallback_locale","path":"app/models/locale_site_setting.rb","lineno":62,"static":true,"thread_id":70097708498960,"parameters":[{"name":"locale","class":"Symbol","object_id":70097724306540,"value":"en_US","kind":"req"}],"receiver":{"class":"Class","object_id":70097569845280,"value":"LocaleSiteSetting"}},{"id":812324,"event":"return","defined_class":"LocaleSiteSetting","method_id":"fallback_locale","path":"app/models/locale_site_setting.rb","lineno":62,"static":true,"thread_id":70097708498960,"parent_id":812323,"elapsed":4.0e-06,"return_value":{"class":"Symbol","value":"en","object_id":3894428}},{"id":812325,"event":"call","defined_class":"LocaleSiteSetting","method_id":"fallback_locale","path":"app/models/locale_site_setting.rb","lineno":62,"static":true,"thread_id":70097708498960,"parameters":[{"name":"locale","class":"Symbol","object_id":3894428,"value":"en","kind":"req"}],"receiver":{"class":"Class","object_id":70097569845280,"value":"LocaleSiteSetting"}},{"id":812326,"event":"return","defined_class":"LocaleSiteSetting","method_id":"fallback_locale","path":"app/models/locale_site_setting.rb","lineno":62,"static":true,"thread_id":70097708498960,"parent_id":812325,"elapsed":1.2e-05},{"id":812327,"event":"call","defined_class":"LocaleSiteSetting","method_id":"fallback_locale","path":"app/models/locale_site_setting.rb","lineno":62,"static":true,"thread_id":70097708498960,"parameters":[{"name":"locale","class":"Symbol","object_id":70097724306540,"value":"en_US","kind":"req"}],"receiver":{"class":"Class","object_id":70097569845280,"value":"LocaleSiteSetting"}},{"id":812328,"event":"return","defined_class":"LocaleSiteSetting","method_id":"fallback_locale","path":"app/models/locale_site_setting.rb","lineno":62,"static":true,"thread_id":70097708498960,"parent_id":812327,"elapsed":4.0e-06,"return_value":{"class":"Symbol","value":"en","object_id":3894428}},{"id":812329,"event":"call","defined_class":"LocaleSiteSetting","method_id":"fallback_locale","path":"app/models/locale_site_setting.rb","lineno":62,"static":true,"thread_id":70097708498960,"parameters":[{"name":"locale","class":"Symbol","object_id":3894428,"value":"en","kind":"req"}],"receiver":{"class":"Class","object_id":70097569845280,"value":"LocaleSiteSetting"}},{"id":812330,"event":"return","defined_class":"LocaleSiteSetting","method_id":"fallback_locale","path":"app/models/locale_site_setting.rb","lineno":62,"static":true,"thread_id":70097708498960,"parent_id":812329,"elapsed":8.0e-06},{"id":812331,"event":"return","defined_class":"ApplicationController","method_id":"set_locale","path":"app/controllers/application_controller.rb","lineno":328,"static":false,"thread_id":70097708498960,"parent_id":812320,"elapsed":0.00063,"return_value":{"class":"Array","value":"[:en_US, :en]","object_id":70097732831900}},{"id":812332,"event":"call","defined_class":"ApplicationController","method_id":"set_mobile_view","path":"app/controllers/application_controller.rb","lineno":368,"static":false,"thread_id":70097708498960,"parameters":[],"receiver":{"class":"UsersController","object_id":70097732515280,"value":"#<UsersController:0x00007f81cce46ba0>"}},{"id":812333,"event":"return","defined_class":"ApplicationController","method_id":"set_mobile_view","path":"app/controllers/application_controller.rb","lineno":368,"static":false,"thread_id":70097708498960,"parent_id":812332,"elapsed":8.0e-06},{"id":812334,"event":"call","defined_class":"Auth::DefaultCurrentUserProvider","method_id":"is_api?","path":"lib/auth/default_current_user_provider.rb","lineno":271,"static":false,"thread_id":70097708498960,"parameters":[],"receiver":{"class":"TestCurrentUserProvider","object_id":70097732732120,"value":"#<TestCurrentUserProvider:0x00007f81cceb09b0>"}},{"id":812335,"event":"call","defined_class":"Auth::DefaultCurrentUserProvider","method_id":"current_user","path":"lib/auth/default_current_user_provider.rb","lineno":61,"static":false,"thread_id":70097708498960,"parameters":[],"receiver":{"class":"TestCurrentUserProvider","object_id":70097732732120,"value":"#<TestCurrentUserProvider:0x00007f81cceb09b0>"}},{"id":812336,"event":"return","defined_class":"Auth::DefaultCurrentUserProvider","method_id":"current_user","path":"lib/auth/default_current_user_provider.rb","lineno":61,"static":false,"thread_id":70097708498960,"parent_id":812335,"elapsed":4.0e-06},{"id":812337,"event":"return","defined_class":"Auth::DefaultCurrentUserProvider","method_id":"is_api?","path":"lib/auth/default_current_user_provider.rb","lineno":271,"static":false,"thread_id":70097708498960,"parent_id":812334,"elapsed":0.000128},{"id":812338,"event":"call","defined_class":"Auth::DefaultCurrentUserProvider","method_id":"current_user","path":"lib/auth/default_current_user_provider.rb","lineno":61,"static":false,"thread_id":70097708498960,"parameters":[],"receiver":{"class":"TestCurrentUserProvider","object_id":70097732732120,"value":"#<TestCurrentUserProvider:0x00007f81cceb09b0>"}},{"id":812339,"event":"return","defined_class":"Auth::DefaultCurrentUserProvider","method_id":"current_user","path":"lib/auth/default_current_user_provider.rb","lineno":61,"static":false,"thread_id":70097708498960,"parent_id":812338,"elapsed":3.0e-06},{"id":812340,"event":"call","defined_class":"Auth::DefaultCurrentUserProvider","method_id":"current_user","path":"lib/auth/default_current_user_provider.rb","lineno":61,"static":false,"thread_id":70097708498960,"parameters":[],"receiver":{"class":"TestCurrentUserProvider","object_id":70097732732120,"value":"#<TestCurrentUserProvider:0x00007f81cceb09b0>"}},{"id":812341,"event":"return","defined_class":"Auth::DefaultCurrentUserProvider","method_id":"current_user","path":"lib/auth/default_current_user_provider.rb","lineno":61,"static":false,"thread_id":70097708498960,"parent_id":812340,"elapsed":3.0e-06},{"id":812342,"event":"call","defined_class":"Auth::DefaultCurrentUserProvider","method_id":"current_user","path":"lib/auth/default_current_user_provider.rb","lineno":61,"static":false,"thread_id":70097708498960,"parameters":[],"receiver":{"class":"TestCurrentUserProvider","object_id":70097732732120,"value":"#<TestCurrentUserProvider:0x00007f81cceb09b0>"}},{"id":812343,"event":"return","defined_class":"Auth::DefaultCurrentUserProvider","method_id":"current_user","path":"lib/auth/default_current_user_provider.rb","lineno":61,"static":false,"thread_id":70097708498960,"parent_id":812342,"elapsed":4.0e-06},{"id":812344,"event":"call","defined_class":"ApplicationController","method_id":"requires_login_arg","path":"app/controllers/application_controller.rb","lineno":669,"static":true,"thread_id":70097708498960,"parameters":[],"receiver":{"class":"Class","object_id":70097775906280,"value":"UsersController"}},{"id":812345,"event":"return","defined_class":"ApplicationController","method_id":"requires_login_arg","path":"app/controllers/application_controller.rb","lineno":669,"static":true,"thread_id":70097708498960,"parent_id":812344,"elapsed":4.0e-06,"return_value":{"class":"Hash","value":"{:only=>[:username, :update, :user_preferences_redirect, :upload_user_image, :pick_avatar, :destroy_","object_id":70097777085280}},{"id":812346,"event":"call","defined_class":"Auth::DefaultCurrentUserProvider","method_id":"current_user","path":"lib/auth/default_current_user_provider.rb","lineno":61,"static":false,"thread_id":70097708498960,"parameters":[],"receiver":{"class":"TestCurrentUserProvider","object_id":70097732732120,"value":"#<TestCurrentUserProvider:0x00007f81cceb09b0>"}},{"id":812347,"event":"return","defined_class":"Auth::DefaultCurrentUserProvider","method_id":"current_user","path":"lib/auth/default_current_user_provider.rb","lineno":61,"static":false,"thread_id":70097708498960,"parent_id":812346,"elapsed":4.0e-06},{"id":812348,"event":"call","defined_class":"ApplicationController","method_id":"rescue_discourse_actions","path":"app/controllers/application_controller.rb","lineno":229,"static":false,"thread_id":70097708498960,"parameters":[{"name":"type","class":"Symbol","object_id":16368348,"value":"not_logged_in","kind":"req"},{"name":"status_code","class":"Integer","object_id":807,"value":"403","kind":"req"},{"name":"opts","class":"Hash","object_id":70097731635200,"value":"{:include_ember=>true}","kind":"opt"}],"receiver":{"class":"UsersController","object_id":70097732515280,"value":"#<UsersController:0x00007f81cce46ba0>"}},{"id":812349,"event":"call","defined_class":"LocaleSiteSetting","method_id":"fallback_locale","path":"app/models/locale_site_setting.rb","lineno":62,"static":true,"thread_id":70097708498960,"parameters":[{"name":"locale","class":"Symbol","object_id":70097724306540,"value":"en_US","kind":"req"}],"receiver":{"class":"Class","object_id":70097569845280,"value":"LocaleSiteSetting"}},{"id":812350,"event":"return","defined_class":"LocaleSiteSetting","method_id":"fallback_locale","path":"app/models/locale_site_setting.rb","lineno":62,"static":true,"thread_id":70097708498960,"parent_id":812349,"elapsed":4.0e-06,"return_value":{"class":"Symbol","value":"en","object_id":3894428}},{"id":812351,"event":"call","defined_class":"LocaleSiteSetting","method_id":"fallback_locale","path":"app/models/locale_site_setting.rb","lineno":62,"static":true,"thread_id":70097708498960,"parameters":[{"name":"locale","class":"Symbol","object_id":3894428,"value":"en","kind":"req"}],"receiver":{"class":"Class","object_id":70097569845280,"value":"LocaleSiteSetting"}},{"id":812352,"event":"return","defined_class":"LocaleSiteSetting","method_id":"fallback_locale","path":"app/models/locale_site_setting.rb","lineno":62,"static":true,"thread_id":70097708498960,"parent_id":812351,"elapsed":1.0e-05},{"id":812353,"event":"call","defined_class":"GlobalSetting","method_id":"skip_db?","path":"app/models/global_setting.rb","lineno":84,"static":true,"thread_id":70097708498960,"parameters":[],"receiver":{"class":"Class","object_id":70097703221560,"value":"GlobalSetting"}},{"id":812354,"event":"return","defined_class":"GlobalSetting","method_id":"skip_db?","path":"app/models/global_setting.rb","lineno":84,"static":true,"thread_id":70097708498960,"parent_id":812353,"elapsed":4.0e-06},{"id":812355,"event":"call","defined_class":"GlobalSetting","method_id":"skip_db?","path":"app/models/global_setting.rb","lineno":84,"static":true,"thread_id":70097708498960,"parameters":[],"receiver":{"class":"Class","object_id":70097703221560,"value":"GlobalSetting"}},{"id":812356,"event":"return","defined_class":"GlobalSetting","method_id":"skip_db?","path":"app/models/global_setting.rb","lineno":84,"static":true,"thread_id":70097708498960,"parent_id":812355,"elapsed":2.4e-05},{"id":812357,"event":"call","defined_class":"LocaleSiteSetting","method_id":"fallback_locale","path":"app/models/locale_site_setting.rb","lineno":62,"static":true,"thread_id":70097708498960,"parameters":[{"name":"locale","class":"Symbol","object_id":70097724306540,"value":"en_US","kind":"req"}],"receiver":{"class":"Class","object_id":70097569845280,"value":"LocaleSiteSetting"}},{"id":812358,"event":"return","defined_class":"LocaleSiteSetting","method_id":"fallback_locale","path":"app/models/locale_site_setting.rb","lineno":62,"static":true,"thread_id":70097708498960,"parent_id":812357,"elapsed":4.0e-06,"return_value":{"class":"Symbol","value":"en","object_id":3894428}},{"id":812359,"event":"call","defined_class":"LocaleSiteSetting","method_id":"fallback_locale","path":"app/models/locale_site_setting.rb","lineno":62,"static":true,"thread_id":70097708498960,"parameters":[{"name":"locale","class":"Symbol","object_id":3894428,"value":"en","kind":"req"}],"receiver":{"class":"Class","object_id":70097569845280,"value":"LocaleSiteSetting"}},{"id":812360,"event":"return","defined_class":"LocaleSiteSetting","method_id":"fallback_locale","path":"app/models/locale_site_setting.rb","lineno":62,"static":true,"thread_id":70097708498960,"parent_id":812359,"elapsed":7.0e-06},{"id":812361,"event":"call","defined_class":"GlobalSetting","method_id":"skip_db?","path":"app/models/global_setting.rb","lineno":84,"static":true,"thread_id":70097708498960,"parameters":[],"receiver":{"class":"Class","object_id":70097703221560,"value":"GlobalSetting"}},{"id":812362,"event":"return","defined_class":"GlobalSetting","method_id":"skip_db?","path":"app/models/global_setting.rb","lineno":84,"static":true,"thread_id":70097708498960,"parent_id":812361,"elapsed":3.0e-06},{"id":812363,"event":"call","defined_class":"GlobalSetting","method_id":"skip_db?","path":"app/models/global_setting.rb","lineno":84,"static":true,"thread_id":70097708498960,"parameters":[],"receiver":{"class":"Class","object_id":70097703221560,"value":"GlobalSetting"}},{"id":812364,"event":"return","defined_class":"GlobalSetting","method_id":"skip_db?","path":"app/models/global_setting.rb","lineno":84,"static":true,"thread_id":70097708498960,"parent_id":812363,"elapsed":3.0e-06},{"id":812365,"event":"return","defined_class":"ApplicationController","method_id":"rescue_discourse_actions","path":"app/controllers/application_controller.rb","lineno":229,"static":false,"thread_id":70097708498960,"parent_id":812348,"elapsed":0.001189,"return_value":{"class":"String","value":"{\"errors\":[\"You need to be logged in to do that.\"],\"error_type\":\"not_logged_in\"}","object_id":70097732837480}},{"id":812366,"event":"return","defined_class":"AppMap::Rails::ActionHandler::HTTPServerResponse","method_id":"call","path":"/Users/kgilpin/source/appland/appmap-ruby/lib/appmap/rails/action_handler.rb","lineno":85,"static":false,"thread_id":70097708498960,"parent_id":812295,"elapsed":0.005648,"http_server_response":{"status":403}},{"id":812367,"event":"call","defined_class":"Auth::DefaultCurrentUserProvider","method_id":"has_auth_cookie?","path":"lib/auth/default_current_user_provider.rb","lineno":281,"static":false,"thread_id":70097708498960,"parameters":[],"receiver":{"class":"TestCurrentUserProvider","object_id":70097732872640,"value":"#<TestCurrentUserProvider:0x00007f81ccef5380>"}},{"id":812368,"event":"return","defined_class":"Auth::DefaultCurrentUserProvider","method_id":"has_auth_cookie?","path":"lib/auth/default_current_user_provider.rb","lineno":281,"static":false,"thread_id":70097708498960,"parent_id":812367,"elapsed":7.0e-06},{"id":812369,"event":"call","defined_class":"ApplicationRequest(id: integer, date: date, req_type: integer, count: integer)","method_id":"increment!","path":"app/models/application_request.rb","lineno":26,"static":true,"thread_id":70097708498960,"parameters":[{"name":"type","class":"Symbol","object_id":13040028,"value":"http_total","kind":"req"},{"name":"opts","class":"NilClass","object_id":8,"value":null,"kind":"opt"}],"receiver":{"class":"Class","object_id":70097802320860,"value":"ApplicationRequest"}},{"id":812370,"event":"return","defined_class":"ApplicationRequest(id: integer, date: date, req_type: integer, count: integer)","method_id":"increment!","path":"app/models/application_request.rb","lineno":26,"static":true,"thread_id":70097708498960,"parent_id":812369,"elapsed":5.0e-06},{"id":812371,"event":"call","defined_class":"ApplicationRequest(id: integer, date: date, req_type: integer, count: integer)","method_id":"increment!","path":"app/models/application_request.rb","lineno":26,"static":true,"thread_id":70097708498960,"parameters":[{"name":"type","class":"Symbol","object_id":13041308,"value":"http_4xx","kind":"req"},{"name":"opts","class":"NilClass","object_id":8,"value":null,"kind":"opt"}],"receiver":{"class":"Class","object_id":70097802320860,"value":"ApplicationRequest"}},{"id":812372,"event":"return","defined_class":"ApplicationRequest(id: integer, date: date, req_type: integer, count: integer)","method_id":"increment!","path":"app/models/application_request.rb","lineno":26,"static":true,"thread_id":70097708498960,"parent_id":812371,"elapsed":3.0e-06}]}